[
   {
      "profile": "lucy driver",
      "plateNumber": "ABC-1234",
      "date": "2025-07-03T10:15:00Z",
      "adminProfile": "admin backup"
   },
   {
      "profile": "jack driver",
      "plateNumber": "XYZ-5678",
      "date": "2025-07-04T08:40:00Z",
      "adminProfile": "jane admin"
   },
   {
      "profile": "driver001",
      "plateNumber": "MDA-2025",
      "date": "2025-07-02T13:20:00Z",
      "adminProfile": "jane admin"
   },
   {
      "profile": "new driver",
      "plateNumber": "RAP-7896",
      "date": "2025-07-01T17:45:00Z",
      "adminProfile": "admin main"
   },
   {
      "profile": "kevin t",
      "plateNumber": "CAR-4321",
      "date": "2025-06-30T11:00:00Z",
      "adminProfile": "admin backup"
   }
]
